{
  "type": "dir",
  "name": "",
  "children": [
    {
      "type": "dir",
      "name": "\"1_\\351\\227\\234\\351\\215\\265\\345\\201\\265\\346\\223\\267\\345\\217\\226",
      "children": [
        {
          "type": "dir",
          "name": "keyframes",
          "children": [
            {
              "type": "file",
              "name": "frame_000000_Scene_Cut.jpg\""
            },
            {
              "type": "file",
              "name": "frame_001184_Scene_Cut.jpg\""
            },
            {
              "type": "file",
              "name": "frame_001185_Object_Appeared.jpg\""
            },
            {
              "type": "file",
              "name": "frame_003078_Object_Appeared.jpg\""
            },
            {
              "type": "file",
              "name": "frame_011983_Scene_Cut.jpg\""
            }
          ]
        },
        {
          "type": "file",
          "name": "analyze.py\""
        },
        {
          "type": "file",
          "name": "requirements.txt\""
        },
        {
          "type": "file",
          "name": "test.mp4\""
        },
        {
          "type": "file",
          "name": "test_analysis.csv\""
        },
        {
          "type": "file",
          "name": "yolov8n.pt\""
        }
      ]
    },
    {
      "type": "dir",
      "name": "\"2_\\351\\200\\220\\345\\255\\227\\347\\250\\277\\346\\223\\267\\345\\217\\226",
      "children": [
        {
          "type": "file",
          "name": "test.mp4\""
        },
        {
          "type": "file",
          "name": "transcribe.py\""
        },
        {
          "type": "file",
          "name": "transcript.csv\""
        }
      ]
    },
    {
      "type": "dir",
      "name": "\"3_\\351\\200\\220\\345\\255\\227\\347\\250\\277\\345\\234\\226\\347\\211\\207\\346\\223\\267\\345\\217\\226",
      "children": [
        {
          "type": "dir",
          "name": "screenshots",
          "children": [
            {
              "type": "file",
              "name": "img_100_end.jpg\""
            },
            {
              "type": "file",
              "name": "img_100_start.jpg\""
            },
            {
              "type": "file",
              "name": "img_101_end.jpg\""
            },
            {
              "type": "file",
              "name": "img_101_start.jpg\""
            },
            {
              "type": "file",
              "name": "img_102_end.jpg\""
            },
            {
              "type": "file",
              "name": "img_102_start.jpg\""
            },
            {
              "type": "file",
              "name": "img_103_end.jpg\""
            },
            {
              "type": "file",
              "name": "img_103_start.jpg\""
            },
            {
              "type": "file",
              "name": "img_104_end.jpg\""
            },
            {
              "type": "file",
              "name": "img_104_start.jpg\""
            },
            {
              "type": "file",
              "name": "img_105_end.jpg\""
            },
            {
              "type": "file",
              "name": "img_105_start.jpg\""
            },
            {
              "type": "file",
              "name": "img_106_end.jpg\""
            },
            {
              "type": "file",
              "name": "img_106_start.jpg\""
            },
            {
              "type": "file",
              "name": "img_107_end.jpg\""
            },
            {
              "type": "file",
              "name": "img_107_start.jpg\""
            },
            {
              "type": "file",
              "name": "img_108_end.jpg\""
            },
            {
              "type": "file",
              "name": "img_108_start.jpg\""
            },
            {
              "type": "file",
              "name": "img_109_end.jpg\""
            },
            {
              "type": "file",
              "name": "img_109_start.jpg\""
            },
            {
              "type": "file",
              "name": "img_10_end.jpg\""
            },
            {
              "type": "file",
              "name": "img_10_start.jpg\""
            },
            {
              "type": "file",
              "name": "img_110_end.jpg\""
            },
            {
              "type": "file",
              "name": "img_110_start.jpg\""
            },
            {
              "type": "file",
              "name": "img_111_end.jpg\""
            },
            {
              "type": "file",
              "name": "img_111_start.jpg\""
            },
            {
              "type": "file",
              "name": "img_112_end.jpg\""
            },
            {
              "type": "file",
              "name": "img_112_start.jpg\""
            },
            {
              "type": "file",
              "name": "img_113_end.jpg\""
            },
            {
              "type": "file",
              "name": "img_113_start.jpg\""
            },
            {
              "type": "file",
              "name": "img_114_end.jpg\""
            },
            {
              "type": "file",
              "name": "img_114_start.jpg\""
            },
            {
              "type": "file",
              "name": "img_115_end.jpg\""
            },
            {
              "type": "file",
              "name": "img_115_start.jpg\""
            },
            {
              "type": "file",
              "name": "img_116_end.jpg\""
            },
            {
              "type": "file",
              "name": "img_116_start.jpg\""
            },
            {
              "type": "file",
              "name": "img_117_end.jpg\""
            },
            {
              "type": "file",
              "name": "img_117_start.jpg\""
            },
            {
              "type": "file",
              "name": "img_118_end.jpg\""
            },
            {
              "type": "file",
              "name": "img_118_start.jpg\""
            },
            {
              "type": "file",
              "name": "img_119_end.jpg\""
            },
            {
              "type": "file",
              "name": "img_119_start.jpg\""
            },
            {
              "type": "file",
              "name": "img_11_end.jpg\""
            },
            {
              "type": "file",
              "name": "img_11_start.jpg\""
            },
            {
              "type": "file",
              "name": "img_120_end.jpg\""
            },
            {
              "type": "file",
              "name": "img_120_start.jpg\""
            },
            {
              "type": "file",
              "name": "img_121_end.jpg\""
            },
            {
              "type": "file",
              "name": "img_121_start.jpg\""
            },
            {
              "type": "file",
              "name": "img_122_end.jpg\""
            },
            {
              "type": "file",
              "name": "img_122_start.jpg\""
            },
            {
              "type": "file",
              "name": "img_123_end.jpg\""
            },
            {
              "type": "file",
              "name": "img_123_start.jpg\""
            },
            {
              "type": "file",
              "name": "img_124_end.jpg\""
            },
            {
              "type": "file",
              "name": "img_124_start.jpg\""
            },
            {
              "type": "file",
              "name": "img_125_end.jpg\""
            },
            {
              "type": "file",
              "name": "img_125_start.jpg\""
            },
            {
              "type": "file",
              "name": "img_126_end.jpg\""
            },
            {
              "type": "file",
              "name": "img_126_start.jpg\""
            },
            {
              "type": "file",
              "name": "img_127_end.jpg\""
            },
            {
              "type": "file",
              "name": "img_127_start.jpg\""
            },
            {
              "type": "file",
              "name": "img_128_end.jpg\""
            },
            {
              "type": "file",
              "name": "img_128_start.jpg\""
            },
            {
              "type": "file",
              "name": "img_129_end.jpg\""
            },
            {
              "type": "file",
              "name": "img_129_start.jpg\""
            },
            {
              "type": "file",
              "name": "img_12_end.jpg\""
            },
            {
              "type": "file",
              "name": "img_12_start.jpg\""
            },
            {
              "type": "file",
              "name": "img_130_end.jpg\""
            },
            {
              "type": "file",
              "name": "img_130_start.jpg\""
            },
            {
              "type": "file",
              "name": "img_131_end.jpg\""
            },
            {
              "type": "file",
              "name": "img_131_start.jpg\""
            },
            {
              "type": "file",
              "name": "img_132_end.jpg\""
            },
            {
              "type": "file",
              "name": "img_132_start.jpg\""
            },
            {
              "type": "file",
              "name": "img_133_end.jpg\""
            },
            {
              "type": "file",
              "name": "img_133_start.jpg\""
            },
            {
              "type": "file",
              "name": "img_134_end.jpg\""
            },
            {
              "type": "file",
              "name": "img_134_start.jpg\""
            },
            {
              "type": "file",
              "name": "img_135_end.jpg\""
            },
            {
              "type": "file",
              "name": "img_135_start.jpg\""
            },
            {
              "type": "file",
              "name": "img_136_end.jpg\""
            },
            {
              "type": "file",
              "name": "img_136_start.jpg\""
            },
            {
              "type": "file",
              "name": "img_137_end.jpg\""
            },
            {
              "type": "file",
              "name": "img_137_start.jpg\""
            },
            {
              "type": "file",
              "name": "img_138_end.jpg\""
            },
            {
              "type": "file",
              "name": "img_138_start.jpg\""
            },
            {
              "type": "file",
              "name": "img_139_end.jpg\""
            },
            {
              "type": "file",
              "name": "img_139_start.jpg\""
            },
            {
              "type": "file",
              "name": "img_13_end.jpg\""
            },
            {
              "type": "file",
              "name": "img_13_start.jpg\""
            },
            {
              "type": "file",
              "name": "img_140_end.jpg\""
            },
            {
              "type": "file",
              "name": "img_140_start.jpg\""
            },
            {
              "type": "file",
              "name": "img_141_end.jpg\""
            },
            {
              "type": "file",
              "name": "img_141_start.jpg\""
            },
            {
              "type": "file",
              "name": "img_142_end.jpg\""
            },
            {
              "type": "file",
              "name": "img_142_start.jpg\""
            },
            {
              "type": "file",
              "name": "img_143_end.jpg\""
            },
            {
              "type": "file",
              "name": "img_143_start.jpg\""
            },
            {
              "type": "file",
              "name": "img_144_end.jpg\""
            },
            {
              "type": "file",
              "name": "img_144_start.jpg\""
            },
            {
              "type": "file",
              "name": "img_145_end.jpg\""
            },
            {
              "type": "file",
              "name": "img_145_start.jpg\""
            },
            {
              "type": "file",
              "name": "img_146_end.jpg\""
            },
            {
              "type": "file",
              "name": "img_146_start.jpg\""
            },
            {
              "type": "file",
              "name": "img_147_end.jpg\""
            },
            {
              "type": "file",
              "name": "img_147_start.jpg\""
            },
            {
              "type": "file",
              "name": "img_148_end.jpg\""
            },
            {
              "type": "file",
              "name": "img_148_start.jpg\""
            },
            {
              "type": "file",
              "name": "img_149_end.jpg\""
            },
            {
              "type": "file",
              "name": "img_149_start.jpg\""
            },
            {
              "type": "file",
              "name": "img_14_end.jpg\""
            },
            {
              "type": "file",
              "name": "img_14_start.jpg\""
            },
            {
              "type": "file",
              "name": "img_150_end.jpg\""
            },
            {
              "type": "file",
              "name": "img_150_start.jpg\""
            },
            {
              "type": "file",
              "name": "img_151_end.jpg\""
            },
            {
              "type": "file",
              "name": "img_151_start.jpg\""
            },
            {
              "type": "file",
              "name": "img_152_end.jpg\""
            },
            {
              "type": "file",
              "name": "img_152_start.jpg\""
            },
            {
              "type": "file",
              "name": "img_153_end.jpg\""
            },
            {
              "type": "file",
              "name": "img_153_start.jpg\""
            },
            {
              "type": "file",
              "name": "img_154_end.jpg\""
            },
            {
              "type": "file",
              "name": "img_154_start.jpg\""
            },
            {
              "type": "file",
              "name": "img_155_end.jpg\""
            },
            {
              "type": "file",
              "name": "img_155_start.jpg\""
            },
            {
              "type": "file",
              "name": "img_156_end.jpg\""
            },
            {
              "type": "file",
              "name": "img_156_start.jpg\""
            },
            {
              "type": "file",
              "name": "img_157_end.jpg\""
            },
            {
              "type": "file",
              "name": "img_157_start.jpg\""
            },
            {
              "type": "file",
              "name": "img_158_end.jpg\""
            },
            {
              "type": "file",
              "name": "img_158_start.jpg\""
            },
            {
              "type": "file",
              "name": "img_159_end.jpg\""
            },
            {
              "type": "file",
              "name": "img_159_start.jpg\""
            },
            {
              "type": "file",
              "name": "img_15_end.jpg\""
            },
            {
              "type": "file",
              "name": "img_15_start.jpg\""
            },
            {
              "type": "file",
              "name": "img_160_end.jpg\""
            },
            {
              "type": "file",
              "name": "img_160_start.jpg\""
            },
            {
              "type": "file",
              "name": "img_161_end.jpg\""
            },
            {
              "type": "file",
              "name": "img_161_start.jpg\""
            },
            {
              "type": "file",
              "name": "img_162_end.jpg\""
            },
            {
              "type": "file",
              "name": "img_162_start.jpg\""
            },
            {
              "type": "file",
              "name": "img_163_end.jpg\""
            },
            {
              "type": "file",
              "name": "img_163_start.jpg\""
            },
            {
              "type": "file",
              "name": "img_164_end.jpg\""
            },
            {
              "type": "file",
              "name": "img_164_start.jpg\""
            },
            {
              "type": "file",
              "name": "img_165_end.jpg\""
            },
            {
              "type": "file",
              "name": "img_165_start.jpg\""
            },
            {
              "type": "file",
              "name": "img_166_end.jpg\""
            },
            {
              "type": "file",
              "name": "img_166_start.jpg\""
            },
            {
              "type": "file",
              "name": "img_167_end.jpg\""
            },
            {
              "type": "file",
              "name": "img_167_start.jpg\""
            },
            {
              "type": "file",
              "name": "img_168_end.jpg\""
            },
            {
              "type": "file",
              "name": "img_168_start.jpg\""
            },
            {
              "type": "file",
              "name": "img_169_end.jpg\""
            },
            {
              "type": "file",
              "name": "img_169_start.jpg\""
            },
            {
              "type": "file",
              "name": "img_16_end.jpg\""
            },
            {
              "type": "file",
              "name": "img_16_start.jpg\""
            },
            {
              "type": "file",
              "name": "img_170_end.jpg\""
            },
            {
              "type": "file",
              "name": "img_170_start.jpg\""
            },
            {
              "type": "file",
              "name": "img_171_end.jpg\""
            },
            {
              "type": "file",
              "name": "img_171_start.jpg\""
            },
            {
              "type": "file",
              "name": "img_172_end.jpg\""
            },
            {
              "type": "file",
              "name": "img_172_start.jpg\""
            },
            {
              "type": "file",
              "name": "img_17_end.jpg\""
            },
            {
              "type": "file",
              "name": "img_17_start.jpg\""
            },
            {
              "type": "file",
              "name": "img_18_end.jpg\""
            },
            {
              "type": "file",
              "name": "img_18_start.jpg\""
            },
            {
              "type": "file",
              "name": "img_19_end.jpg\""
            },
            {
              "type": "file",
              "name": "img_19_start.jpg\""
            },
            {
              "type": "file",
              "name": "img_1_end.jpg\""
            },
            {
              "type": "file",
              "name": "img_1_start.jpg\""
            },
            {
              "type": "file",
              "name": "img_20_end.jpg\""
            },
            {
              "type": "file",
              "name": "img_20_start.jpg\""
            },
            {
              "type": "file",
              "name": "img_21_end.jpg\""
            },
            {
              "type": "file",
              "name": "img_21_start.jpg\""
            },
            {
              "type": "file",
              "name": "img_22_end.jpg\""
            },
            {
              "type": "file",
              "name": "img_22_start.jpg\""
            },
            {
              "type": "file",
              "name": "img_23_end.jpg\""
            },
            {
              "type": "file",
              "name": "img_23_start.jpg\""
            },
            {
              "type": "file",
              "name": "img_24_end.jpg\""
            },
            {
              "type": "file",
              "name": "img_24_start.jpg\""
            },
            {
              "type": "file",
              "name": "img_25_end.jpg\""
            },
            {
              "type": "file",
              "name": "img_25_start.jpg\""
            },
            {
              "type": "file",
              "name": "img_26_end.jpg\""
            },
            {
              "type": "file",
              "name": "img_26_start.jpg\""
            },
            {
              "type": "file",
              "name": "img_27_end.jpg\""
            },
            {
              "type": "file",
              "name": "img_27_start.jpg\""
            },
            {
              "type": "file",
              "name": "img_28_end.jpg\""
            },
            {
              "type": "file",
              "name": "img_28_start.jpg\""
            },
            {
              "type": "file",
              "name": "img_29_end.jpg\""
            },
            {
              "type": "file",
              "name": "img_29_start.jpg\""
            },
            {
              "type": "file",
              "name": "img_2_end.jpg\""
            },
            {
              "type": "file",
              "name": "img_2_start.jpg\""
            },
            {
              "type": "file",
              "name": "img_30_end.jpg\""
            },
            {
              "type": "file",
              "name": "img_30_start.jpg\""
            },
            {
              "type": "file",
              "name": "img_31_end.jpg\""
            },
            {
              "type": "file",
              "name": "img_31_start.jpg\""
            },
            {
              "type": "file",
              "name": "img_32_end.jpg\""
            },
            {
              "type": "file",
              "name": "img_32_start.jpg\""
            },
            {
              "type": "file",
              "name": "img_33_end.jpg\""
            },
            {
              "type": "file",
              "name": "img_33_start.jpg\""
            },
            {
              "type": "file",
              "name": "img_34_end.jpg\""
            },
            {
              "type": "file",
              "name": "img_34_start.jpg\""
            },
            {
              "type": "file",
              "name": "img_35_end.jpg\""
            },
            {
              "type": "file",
              "name": "img_35_start.jpg\""
            },
            {
              "type": "file",
              "name": "img_36_end.jpg\""
            },
            {
              "type": "file",
              "name": "img_36_start.jpg\""
            },
            {
              "type": "file",
              "name": "img_37_end.jpg\""
            },
            {
              "type": "file",
              "name": "img_37_start.jpg\""
            },
            {
              "type": "file",
              "name": "img_38_end.jpg\""
            },
            {
              "type": "file",
              "name": "img_38_start.jpg\""
            },
            {
              "type": "file",
              "name": "img_39_end.jpg\""
            },
            {
              "type": "file",
              "name": "img_39_start.jpg\""
            },
            {
              "type": "file",
              "name": "img_3_end.jpg\""
            },
            {
              "type": "file",
              "name": "img_3_start.jpg\""
            },
            {
              "type": "file",
              "name": "img_40_end.jpg\""
            },
            {
              "type": "file",
              "name": "img_40_start.jpg\""
            },
            {
              "type": "file",
              "name": "img_41_end.jpg\""
            },
            {
              "type": "file",
              "name": "img_41_start.jpg\""
            },
            {
              "type": "file",
              "name": "img_42_end.jpg\""
            },
            {
              "type": "file",
              "name": "img_42_start.jpg\""
            },
            {
              "type": "file",
              "name": "img_43_end.jpg\""
            },
            {
              "type": "file",
              "name": "img_43_start.jpg\""
            },
            {
              "type": "file",
              "name": "img_44_end.jpg\""
            },
            {
              "type": "file",
              "name": "img_44_start.jpg\""
            },
            {
              "type": "file",
              "name": "img_45_end.jpg\""
            },
            {
              "type": "file",
              "name": "img_45_start.jpg\""
            },
            {
              "type": "file",
              "name": "img_46_end.jpg\""
            },
            {
              "type": "file",
              "name": "img_46_start.jpg\""
            },
            {
              "type": "file",
              "name": "img_47_end.jpg\""
            },
            {
              "type": "file",
              "name": "img_47_start.jpg\""
            },
            {
              "type": "file",
              "name": "img_48_end.jpg\""
            },
            {
              "type": "file",
              "name": "img_48_start.jpg\""
            },
            {
              "type": "file",
              "name": "img_49_end.jpg\""
            },
            {
              "type": "file",
              "name": "img_49_start.jpg\""
            },
            {
              "type": "file",
              "name": "img_4_end.jpg\""
            },
            {
              "type": "file",
              "name": "img_4_start.jpg\""
            },
            {
              "type": "file",
              "name": "img_50_end.jpg\""
            },
            {
              "type": "file",
              "name": "img_50_start.jpg\""
            },
            {
              "type": "file",
              "name": "img_51_end.jpg\""
            },
            {
              "type": "file",
              "name": "img_51_start.jpg\""
            },
            {
              "type": "file",
              "name": "img_52_end.jpg\""
            },
            {
              "type": "file",
              "name": "img_52_start.jpg\""
            },
            {
              "type": "file",
              "name": "img_53_end.jpg\""
            },
            {
              "type": "file",
              "name": "img_53_start.jpg\""
            },
            {
              "type": "file",
              "name": "img_54_end.jpg\""
            },
            {
              "type": "file",
              "name": "img_54_start.jpg\""
            },
            {
              "type": "file",
              "name": "img_55_end.jpg\""
            },
            {
              "type": "file",
              "name": "img_55_start.jpg\""
            },
            {
              "type": "file",
              "name": "img_56_end.jpg\""
            },
            {
              "type": "file",
              "name": "img_56_start.jpg\""
            },
            {
              "type": "file",
              "name": "img_57_end.jpg\""
            },
            {
              "type": "file",
              "name": "img_57_start.jpg\""
            },
            {
              "type": "file",
              "name": "img_58_end.jpg\""
            },
            {
              "type": "file",
              "name": "img_58_start.jpg\""
            },
            {
              "type": "file",
              "name": "img_59_end.jpg\""
            },
            {
              "type": "file",
              "name": "img_59_start.jpg\""
            },
            {
              "type": "file",
              "name": "img_5_end.jpg\""
            },
            {
              "type": "file",
              "name": "img_5_start.jpg\""
            },
            {
              "type": "file",
              "name": "img_60_end.jpg\""
            },
            {
              "type": "file",
              "name": "img_60_start.jpg\""
            },
            {
              "type": "file",
              "name": "img_61_end.jpg\""
            },
            {
              "type": "file",
              "name": "img_61_start.jpg\""
            },
            {
              "type": "file",
              "name": "img_62_end.jpg\""
            },
            {
              "type": "file",
              "name": "img_62_start.jpg\""
            },
            {
              "type": "file",
              "name": "img_63_end.jpg\""
            },
            {
              "type": "file",
              "name": "img_63_start.jpg\""
            },
            {
              "type": "file",
              "name": "img_64_end.jpg\""
            },
            {
              "type": "file",
              "name": "img_64_start.jpg\""
            },
            {
              "type": "file",
              "name": "img_65_end.jpg\""
            },
            {
              "type": "file",
              "name": "img_65_start.jpg\""
            },
            {
              "type": "file",
              "name": "img_66_end.jpg\""
            },
            {
              "type": "file",
              "name": "img_66_start.jpg\""
            },
            {
              "type": "file",
              "name": "img_67_end.jpg\""
            },
            {
              "type": "file",
              "name": "img_67_start.jpg\""
            },
            {
              "type": "file",
              "name": "img_68_end.jpg\""
            },
            {
              "type": "file",
              "name": "img_68_start.jpg\""
            },
            {
              "type": "file",
              "name": "img_69_end.jpg\""
            },
            {
              "type": "file",
              "name": "img_69_start.jpg\""
            },
            {
              "type": "file",
              "name": "img_6_end.jpg\""
            },
            {
              "type": "file",
              "name": "img_6_start.jpg\""
            },
            {
              "type": "file",
              "name": "img_70_end.jpg\""
            },
            {
              "type": "file",
              "name": "img_70_start.jpg\""
            },
            {
              "type": "file",
              "name": "img_71_end.jpg\""
            },
            {
              "type": "file",
              "name": "img_71_start.jpg\""
            },
            {
              "type": "file",
              "name": "img_72_end.jpg\""
            },
            {
              "type": "file",
              "name": "img_72_start.jpg\""
            },
            {
              "type": "file",
              "name": "img_73_end.jpg\""
            },
            {
              "type": "file",
              "name": "img_73_start.jpg\""
            },
            {
              "type": "file",
              "name": "img_74_end.jpg\""
            },
            {
              "type": "file",
              "name": "img_74_start.jpg\""
            },
            {
              "type": "file",
              "name": "img_75_end.jpg\""
            },
            {
              "type": "file",
              "name": "img_75_start.jpg\""
            },
            {
              "type": "file",
              "name": "img_76_end.jpg\""
            },
            {
              "type": "file",
              "name": "img_76_start.jpg\""
            },
            {
              "type": "file",
              "name": "img_77_end.jpg\""
            },
            {
              "type": "file",
              "name": "img_77_start.jpg\""
            },
            {
              "type": "file",
              "name": "img_78_end.jpg\""
            },
            {
              "type": "file",
              "name": "img_78_start.jpg\""
            },
            {
              "type": "file",
              "name": "img_79_end.jpg\""
            },
            {
              "type": "file",
              "name": "img_79_start.jpg\""
            },
            {
              "type": "file",
              "name": "img_7_end.jpg\""
            },
            {
              "type": "file",
              "name": "img_7_start.jpg\""
            },
            {
              "type": "file",
              "name": "img_80_end.jpg\""
            },
            {
              "type": "file",
              "name": "img_80_start.jpg\""
            },
            {
              "type": "file",
              "name": "img_81_end.jpg\""
            },
            {
              "type": "file",
              "name": "img_81_start.jpg\""
            },
            {
              "type": "file",
              "name": "img_82_end.jpg\""
            },
            {
              "type": "file",
              "name": "img_82_start.jpg\""
            },
            {
              "type": "file",
              "name": "img_83_end.jpg\""
            },
            {
              "type": "file",
              "name": "img_83_start.jpg\""
            },
            {
              "type": "file",
              "name": "img_84_end.jpg\""
            },
            {
              "type": "file",
              "name": "img_84_start.jpg\""
            },
            {
              "type": "file",
              "name": "img_85_end.jpg\""
            },
            {
              "type": "file",
              "name": "img_85_start.jpg\""
            },
            {
              "type": "file",
              "name": "img_86_end.jpg\""
            },
            {
              "type": "file",
              "name": "img_86_start.jpg\""
            },
            {
              "type": "file",
              "name": "img_87_end.jpg\""
            },
            {
              "type": "file",
              "name": "img_87_start.jpg\""
            },
            {
              "type": "file",
              "name": "img_88_end.jpg\""
            },
            {
              "type": "file",
              "name": "img_88_start.jpg\""
            },
            {
              "type": "file",
              "name": "img_89_end.jpg\""
            },
            {
              "type": "file",
              "name": "img_89_start.jpg\""
            },
            {
              "type": "file",
              "name": "img_8_end.jpg\""
            },
            {
              "type": "file",
              "name": "img_8_start.jpg\""
            },
            {
              "type": "file",
              "name": "img_90_end.jpg\""
            },
            {
              "type": "file",
              "name": "img_90_start.jpg\""
            },
            {
              "type": "file",
              "name": "img_91_end.jpg\""
            },
            {
              "type": "file",
              "name": "img_91_start.jpg\""
            },
            {
              "type": "file",
              "name": "img_92_end.jpg\""
            },
            {
              "type": "file",
              "name": "img_92_start.jpg\""
            },
            {
              "type": "file",
              "name": "img_93_end.jpg\""
            },
            {
              "type": "file",
              "name": "img_93_start.jpg\""
            },
            {
              "type": "file",
              "name": "img_94_end.jpg\""
            },
            {
              "type": "file",
              "name": "img_94_start.jpg\""
            },
            {
              "type": "file",
              "name": "img_95_end.jpg\""
            },
            {
              "type": "file",
              "name": "img_95_start.jpg\""
            },
            {
              "type": "file",
              "name": "img_96_end.jpg\""
            },
            {
              "type": "file",
              "name": "img_96_start.jpg\""
            },
            {
              "type": "file",
              "name": "img_97_end.jpg\""
            },
            {
              "type": "file",
              "name": "img_97_start.jpg\""
            },
            {
              "type": "file",
              "name": "img_98_end.jpg\""
            },
            {
              "type": "file",
              "name": "img_98_start.jpg\""
            },
            {
              "type": "file",
              "name": "img_99_end.jpg\""
            },
            {
              "type": "file",
              "name": "img_99_start.jpg\""
            },
            {
              "type": "file",
              "name": "img_9_end.jpg\""
            },
            {
              "type": "file",
              "name": "img_9_start.jpg\""
            }
          ]
        },
        {
          "type": "file",
          "name": "extract_screenshots.py\""
        },
        {
          "type": "file",
          "name": "test.mp4\""
        },
        {
          "type": "file",
          "name": "transcript.csv\""
        }
      ]
    },
    {
      "type": "dir",
      "name": "5_RAG_database",
      "children": [
        {
          "type": "dir",
          "name": "__pycache__",
          "children": [
            {
              "type": "file",
              "name": "rag_query.cpython-310.pyc"
            },
            {
              "type": "file",
              "name": "rag_query.cpython-311.pyc"
            }
          ]
        },
        {
          "type": "dir",
          "name": "input",
          "children": [
            {
              "type": "dir",
              "name": "keyframes",
              "children": [
                {
                  "type": "file",
                  "name": "frame_000000_Scene_Cut.jpg"
                },
                {
                  "type": "file",
                  "name": "frame_001184_Scene_Cut.jpg"
                },
                {
                  "type": "file",
                  "name": "frame_001185_Object_Appeared.jpg"
                },
                {
                  "type": "file",
                  "name": "frame_003078_Object_Appeared.jpg"
                },
                {
                  "type": "file",
                  "name": "frame_011983_Scene_Cut.jpg"
                }
              ]
            },
            {
              "type": "dir",
              "name": "screenshots",
              "children": [
                {
                  "type": "file",
                  "name": "img_100_end.jpg"
                },
                {
                  "type": "file",
                  "name": "img_100_start.jpg"
                },
                {
                  "type": "file",
                  "name": "img_101_end.jpg"
                },
                {
                  "type": "file",
                  "name": "img_101_start.jpg"
                },
                {
                  "type": "file",
                  "name": "img_102_end.jpg"
                },
                {
                  "type": "file",
                  "name": "img_102_start.jpg"
                },
                {
                  "type": "file",
                  "name": "img_103_end.jpg"
                },
                {
                  "type": "file",
                  "name": "img_103_start.jpg"
                },
                {
                  "type": "file",
                  "name": "img_104_end.jpg"
                },
                {
                  "type": "file",
                  "name": "img_104_start.jpg"
                },
                {
                  "type": "file",
                  "name": "img_105_end.jpg"
                },
                {
                  "type": "file",
                  "name": "img_105_start.jpg"
                },
                {
                  "type": "file",
                  "name": "img_106_end.jpg"
                },
                {
                  "type": "file",
                  "name": "img_106_start.jpg"
                },
                {
                  "type": "file",
                  "name": "img_107_end.jpg"
                },
                {
                  "type": "file",
                  "name": "img_107_start.jpg"
                },
                {
                  "type": "file",
                  "name": "img_108_end.jpg"
                },
                {
                  "type": "file",
                  "name": "img_108_start.jpg"
                },
                {
                  "type": "file",
                  "name": "img_109_end.jpg"
                },
                {
                  "type": "file",
                  "name": "img_109_start.jpg"
                },
                {
                  "type": "file",
                  "name": "img_10_end.jpg"
                },
                {
                  "type": "file",
                  "name": "img_10_start.jpg"
                },
                {
                  "type": "file",
                  "name": "img_110_end.jpg"
                },
                {
                  "type": "file",
                  "name": "img_110_start.jpg"
                },
                {
                  "type": "file",
                  "name": "img_111_end.jpg"
                },
                {
                  "type": "file",
                  "name": "img_111_start.jpg"
                },
                {
                  "type": "file",
                  "name": "img_112_end.jpg"
                },
                {
                  "type": "file",
                  "name": "img_112_start.jpg"
                },
                {
                  "type": "file",
                  "name": "img_113_end.jpg"
                },
                {
                  "type": "file",
                  "name": "img_113_start.jpg"
                },
                {
                  "type": "file",
                  "name": "img_114_end.jpg"
                },
                {
                  "type": "file",
                  "name": "img_114_start.jpg"
                },
                {
                  "type": "file",
                  "name": "img_115_end.jpg"
                },
                {
                  "type": "file",
                  "name": "img_115_start.jpg"
                },
                {
                  "type": "file",
                  "name": "img_116_end.jpg"
                },
                {
                  "type": "file",
                  "name": "img_116_start.jpg"
                },
                {
                  "type": "file",
                  "name": "img_117_end.jpg"
                },
                {
                  "type": "file",
                  "name": "img_117_start.jpg"
                },
                {
                  "type": "file",
                  "name": "img_118_end.jpg"
                },
                {
                  "type": "file",
                  "name": "img_118_start.jpg"
                },
                {
                  "type": "file",
                  "name": "img_119_end.jpg"
                },
                {
                  "type": "file",
                  "name": "img_119_start.jpg"
                },
                {
                  "type": "file",
                  "name": "img_11_end.jpg"
                },
                {
                  "type": "file",
                  "name": "img_11_start.jpg"
                },
                {
                  "type": "file",
                  "name": "img_120_end.jpg"
                },
                {
                  "type": "file",
                  "name": "img_120_start.jpg"
                },
                {
                  "type": "file",
                  "name": "img_121_end.jpg"
                },
                {
                  "type": "file",
                  "name": "img_121_start.jpg"
                },
                {
                  "type": "file",
                  "name": "img_122_end.jpg"
                },
                {
                  "type": "file",
                  "name": "img_122_start.jpg"
                },
                {
                  "type": "file",
                  "name": "img_123_end.jpg"
                },
                {
                  "type": "file",
                  "name": "img_123_start.jpg"
                },
                {
                  "type": "file",
                  "name": "img_124_end.jpg"
                },
                {
                  "type": "file",
                  "name": "img_124_start.jpg"
                },
                {
                  "type": "file",
                  "name": "img_125_end.jpg"
                },
                {
                  "type": "file",
                  "name": "img_125_start.jpg"
                },
                {
                  "type": "file",
                  "name": "img_126_end.jpg"
                },
                {
                  "type": "file",
                  "name": "img_126_start.jpg"
                },
                {
                  "type": "file",
                  "name": "img_127_end.jpg"
                },
                {
                  "type": "file",
                  "name": "img_127_start.jpg"
                },
                {
                  "type": "file",
                  "name": "img_128_end.jpg"
                },
                {
                  "type": "file",
                  "name": "img_128_start.jpg"
                },
                {
                  "type": "file",
                  "name": "img_129_end.jpg"
                },
                {
                  "type": "file",
                  "name": "img_129_start.jpg"
                },
                {
                  "type": "file",
                  "name": "img_12_end.jpg"
                },
                {
                  "type": "file",
                  "name": "img_12_start.jpg"
                },
                {
                  "type": "file",
                  "name": "img_130_end.jpg"
                },
                {
                  "type": "file",
                  "name": "img_130_start.jpg"
                },
                {
                  "type": "file",
                  "name": "img_131_end.jpg"
                },
                {
                  "type": "file",
                  "name": "img_131_start.jpg"
                },
                {
                  "type": "file",
                  "name": "img_132_end.jpg"
                },
                {
                  "type": "file",
                  "name": "img_132_start.jpg"
                },
                {
                  "type": "file",
                  "name": "img_133_end.jpg"
                },
                {
                  "type": "file",
                  "name": "img_133_start.jpg"
                },
                {
                  "type": "file",
                  "name": "img_134_end.jpg"
                },
                {
                  "type": "file",
                  "name": "img_134_start.jpg"
                },
                {
                  "type": "file",
                  "name": "img_135_end.jpg"
                },
                {
                  "type": "file",
                  "name": "img_135_start.jpg"
                },
                {
                  "type": "file",
                  "name": "img_136_end.jpg"
                },
                {
                  "type": "file",
                  "name": "img_136_start.jpg"
                },
                {
                  "type": "file",
                  "name": "img_137_end.jpg"
                },
                {
                  "type": "file",
                  "name": "img_137_start.jpg"
                },
                {
                  "type": "file",
                  "name": "img_138_end.jpg"
                },
                {
                  "type": "file",
                  "name": "img_138_start.jpg"
                },
                {
                  "type": "file",
                  "name": "img_139_end.jpg"
                },
                {
                  "type": "file",
                  "name": "img_139_start.jpg"
                },
                {
                  "type": "file",
                  "name": "img_13_end.jpg"
                },
                {
                  "type": "file",
                  "name": "img_13_start.jpg"
                },
                {
                  "type": "file",
                  "name": "img_140_end.jpg"
                },
                {
                  "type": "file",
                  "name": "img_140_start.jpg"
                },
                {
                  "type": "file",
                  "name": "img_141_end.jpg"
                },
                {
                  "type": "file",
                  "name": "img_141_start.jpg"
                },
                {
                  "type": "file",
                  "name": "img_142_end.jpg"
                },
                {
                  "type": "file",
                  "name": "img_142_start.jpg"
                },
                {
                  "type": "file",
                  "name": "img_143_end.jpg"
                },
                {
                  "type": "file",
                  "name": "img_143_start.jpg"
                },
                {
                  "type": "file",
                  "name": "img_144_end.jpg"
                },
                {
                  "type": "file",
                  "name": "img_144_start.jpg"
                },
                {
                  "type": "file",
                  "name": "img_145_end.jpg"
                },
                {
                  "type": "file",
                  "name": "img_145_start.jpg"
                },
                {
                  "type": "file",
                  "name": "img_146_end.jpg"
                },
                {
                  "type": "file",
                  "name": "img_146_start.jpg"
                },
                {
                  "type": "file",
                  "name": "img_147_end.jpg"
                },
                {
                  "type": "file",
                  "name": "img_147_start.jpg"
                },
                {
                  "type": "file",
                  "name": "img_148_end.jpg"
                },
                {
                  "type": "file",
                  "name": "img_148_start.jpg"
                },
                {
                  "type": "file",
                  "name": "img_149_end.jpg"
                },
                {
                  "type": "file",
                  "name": "img_149_start.jpg"
                },
                {
                  "type": "file",
                  "name": "img_14_end.jpg"
                },
                {
                  "type": "file",
                  "name": "img_14_start.jpg"
                },
                {
                  "type": "file",
                  "name": "img_150_end.jpg"
                },
                {
                  "type": "file",
                  "name": "img_150_start.jpg"
                },
                {
                  "type": "file",
                  "name": "img_151_end.jpg"
                },
                {
                  "type": "file",
                  "name": "img_151_start.jpg"
                },
                {
                  "type": "file",
                  "name": "img_152_end.jpg"
                },
                {
                  "type": "file",
                  "name": "img_152_start.jpg"
                },
                {
                  "type": "file",
                  "name": "img_153_end.jpg"
                },
                {
                  "type": "file",
                  "name": "img_153_start.jpg"
                },
                {
                  "type": "file",
                  "name": "img_154_end.jpg"
                },
                {
                  "type": "file",
                  "name": "img_154_start.jpg"
                },
                {
                  "type": "file",
                  "name": "img_155_end.jpg"
                },
                {
                  "type": "file",
                  "name": "img_155_start.jpg"
                },
                {
                  "type": "file",
                  "name": "img_156_end.jpg"
                },
                {
                  "type": "file",
                  "name": "img_156_start.jpg"
                },
                {
                  "type": "file",
                  "name": "img_157_end.jpg"
                },
                {
                  "type": "file",
                  "name": "img_157_start.jpg"
                },
                {
                  "type": "file",
                  "name": "img_158_end.jpg"
                },
                {
                  "type": "file",
                  "name": "img_158_start.jpg"
                },
                {
                  "type": "file",
                  "name": "img_159_end.jpg"
                },
                {
                  "type": "file",
                  "name": "img_159_start.jpg"
                },
                {
                  "type": "file",
                  "name": "img_15_end.jpg"
                },
                {
                  "type": "file",
                  "name": "img_15_start.jpg"
                },
                {
                  "type": "file",
                  "name": "img_160_end.jpg"
                },
                {
                  "type": "file",
                  "name": "img_160_start.jpg"
                },
                {
                  "type": "file",
                  "name": "img_161_end.jpg"
                },
                {
                  "type": "file",
                  "name": "img_161_start.jpg"
                },
                {
                  "type": "file",
                  "name": "img_162_end.jpg"
                },
                {
                  "type": "file",
                  "name": "img_162_start.jpg"
                },
                {
                  "type": "file",
                  "name": "img_163_end.jpg"
                },
                {
                  "type": "file",
                  "name": "img_163_start.jpg"
                },
                {
                  "type": "file",
                  "name": "img_164_end.jpg"
                },
                {
                  "type": "file",
                  "name": "img_164_start.jpg"
                },
                {
                  "type": "file",
                  "name": "img_165_end.jpg"
                },
                {
                  "type": "file",
                  "name": "img_165_start.jpg"
                },
                {
                  "type": "file",
                  "name": "img_166_end.jpg"
                },
                {
                  "type": "file",
                  "name": "img_166_start.jpg"
                },
                {
                  "type": "file",
                  "name": "img_167_end.jpg"
                },
                {
                  "type": "file",
                  "name": "img_167_start.jpg"
                },
                {
                  "type": "file",
                  "name": "img_168_end.jpg"
                },
                {
                  "type": "file",
                  "name": "img_168_start.jpg"
                },
                {
                  "type": "file",
                  "name": "img_169_end.jpg"
                },
                {
                  "type": "file",
                  "name": "img_169_start.jpg"
                },
                {
                  "type": "file",
                  "name": "img_16_end.jpg"
                },
                {
                  "type": "file",
                  "name": "img_16_start.jpg"
                },
                {
                  "type": "file",
                  "name": "img_170_end.jpg"
                },
                {
                  "type": "file",
                  "name": "img_170_start.jpg"
                },
                {
                  "type": "file",
                  "name": "img_171_end.jpg"
                },
                {
                  "type": "file",
                  "name": "img_171_start.jpg"
                },
                {
                  "type": "file",
                  "name": "img_172_end.jpg"
                },
                {
                  "type": "file",
                  "name": "img_172_start.jpg"
                },
                {
                  "type": "file",
                  "name": "img_17_end.jpg"
                },
                {
                  "type": "file",
                  "name": "img_17_start.jpg"
                },
                {
                  "type": "file",
                  "name": "img_18_end.jpg"
                },
                {
                  "type": "file",
                  "name": "img_18_start.jpg"
                },
                {
                  "type": "file",
                  "name": "img_19_end.jpg"
                },
                {
                  "type": "file",
                  "name": "img_19_start.jpg"
                },
                {
                  "type": "file",
                  "name": "img_1_end.jpg"
                },
                {
                  "type": "file",
                  "name": "img_1_start.jpg"
                },
                {
                  "type": "file",
                  "name": "img_20_end.jpg"
                },
                {
                  "type": "file",
                  "name": "img_20_start.jpg"
                },
                {
                  "type": "file",
                  "name": "img_21_end.jpg"
                },
                {
                  "type": "file",
                  "name": "img_21_start.jpg"
                },
                {
                  "type": "file",
                  "name": "img_22_end.jpg"
                },
                {
                  "type": "file",
                  "name": "img_22_start.jpg"
                },
                {
                  "type": "file",
                  "name": "img_23_end.jpg"
                },
                {
                  "type": "file",
                  "name": "img_23_start.jpg"
                },
                {
                  "type": "file",
                  "name": "img_24_end.jpg"
                },
                {
                  "type": "file",
                  "name": "img_24_start.jpg"
                },
                {
                  "type": "file",
                  "name": "img_25_end.jpg"
                },
                {
                  "type": "file",
                  "name": "img_25_start.jpg"
                },
                {
                  "type": "file",
                  "name": "img_26_end.jpg"
                },
                {
                  "type": "file",
                  "name": "img_26_start.jpg"
                },
                {
                  "type": "file",
                  "name": "img_27_end.jpg"
                },
                {
                  "type": "file",
                  "name": "img_27_start.jpg"
                },
                {
                  "type": "file",
                  "name": "img_28_end.jpg"
                },
                {
                  "type": "file",
                  "name": "img_28_start.jpg"
                },
                {
                  "type": "file",
                  "name": "img_29_end.jpg"
                },
                {
                  "type": "file",
                  "name": "img_29_start.jpg"
                },
                {
                  "type": "file",
                  "name": "img_2_end.jpg"
                },
                {
                  "type": "file",
                  "name": "img_2_start.jpg"
                },
                {
                  "type": "file",
                  "name": "img_30_end.jpg"
                },
                {
                  "type": "file",
                  "name": "img_30_start.jpg"
                },
                {
                  "type": "file",
                  "name": "img_31_end.jpg"
                },
                {
                  "type": "file",
                  "name": "img_31_start.jpg"
                },
                {
                  "type": "file",
                  "name": "img_32_end.jpg"
                },
                {
                  "type": "file",
                  "name": "img_32_start.jpg"
                },
                {
                  "type": "file",
                  "name": "img_33_end.jpg"
                },
                {
                  "type": "file",
                  "name": "img_33_start.jpg"
                },
                {
                  "type": "file",
                  "name": "img_34_end.jpg"
                },
                {
                  "type": "file",
                  "name": "img_34_start.jpg"
                },
                {
                  "type": "file",
                  "name": "img_35_end.jpg"
                },
                {
                  "type": "file",
                  "name": "img_35_start.jpg"
                },
                {
                  "type": "file",
                  "name": "img_36_end.jpg"
                },
                {
                  "type": "file",
                  "name": "img_36_start.jpg"
                },
                {
                  "type": "file",
                  "name": "img_37_end.jpg"
                },
                {
                  "type": "file",
                  "name": "img_37_start.jpg"
                },
                {
                  "type": "file",
                  "name": "img_38_end.jpg"
                },
                {
                  "type": "file",
                  "name": "img_38_start.jpg"
                },
                {
                  "type": "file",
                  "name": "img_39_end.jpg"
                },
                {
                  "type": "file",
                  "name": "img_39_start.jpg"
                },
                {
                  "type": "file",
                  "name": "img_3_end.jpg"
                },
                {
                  "type": "file",
                  "name": "img_3_start.jpg"
                },
                {
                  "type": "file",
                  "name": "img_40_end.jpg"
                },
                {
                  "type": "file",
                  "name": "img_40_start.jpg"
                },
                {
                  "type": "file",
                  "name": "img_41_end.jpg"
                },
                {
                  "type": "file",
                  "name": "img_41_start.jpg"
                },
                {
                  "type": "file",
                  "name": "img_42_end.jpg"
                },
                {
                  "type": "file",
                  "name": "img_42_start.jpg"
                },
                {
                  "type": "file",
                  "name": "img_43_end.jpg"
                },
                {
                  "type": "file",
                  "name": "img_43_start.jpg"
                },
                {
                  "type": "file",
                  "name": "img_44_end.jpg"
                },
                {
                  "type": "file",
                  "name": "img_44_start.jpg"
                },
                {
                  "type": "file",
                  "name": "img_45_end.jpg"
                },
                {
                  "type": "file",
                  "name": "img_45_start.jpg"
                },
                {
                  "type": "file",
                  "name": "img_46_end.jpg"
                },
                {
                  "type": "file",
                  "name": "img_46_start.jpg"
                },
                {
                  "type": "file",
                  "name": "img_47_end.jpg"
                },
                {
                  "type": "file",
                  "name": "img_47_start.jpg"
                },
                {
                  "type": "file",
                  "name": "img_48_end.jpg"
                },
                {
                  "type": "file",
                  "name": "img_48_start.jpg"
                },
                {
                  "type": "file",
                  "name": "img_49_end.jpg"
                },
                {
                  "type": "file",
                  "name": "img_49_start.jpg"
                },
                {
                  "type": "file",
                  "name": "img_4_end.jpg"
                },
                {
                  "type": "file",
                  "name": "img_4_start.jpg"
                },
                {
                  "type": "file",
                  "name": "img_50_end.jpg"
                },
                {
                  "type": "file",
                  "name": "img_50_start.jpg"
                },
                {
                  "type": "file",
                  "name": "img_51_end.jpg"
                },
                {
                  "type": "file",
                  "name": "img_51_start.jpg"
                },
                {
                  "type": "file",
                  "name": "img_52_end.jpg"
                },
                {
                  "type": "file",
                  "name": "img_52_start.jpg"
                },
                {
                  "type": "file",
                  "name": "img_53_end.jpg"
                },
                {
                  "type": "file",
                  "name": "img_53_start.jpg"
                },
                {
                  "type": "file",
                  "name": "img_54_end.jpg"
                },
                {
                  "type": "file",
                  "name": "img_54_start.jpg"
                },
                {
                  "type": "file",
                  "name": "img_55_end.jpg"
                },
                {
                  "type": "file",
                  "name": "img_55_start.jpg"
                },
                {
                  "type": "file",
                  "name": "img_56_end.jpg"
                },
                {
                  "type": "file",
                  "name": "img_56_start.jpg"
                },
                {
                  "type": "file",
                  "name": "img_57_end.jpg"
                },
                {
                  "type": "file",
                  "name": "img_57_start.jpg"
                },
                {
                  "type": "file",
                  "name": "img_58_end.jpg"
                },
                {
                  "type": "file",
                  "name": "img_58_start.jpg"
                },
                {
                  "type": "file",
                  "name": "img_59_end.jpg"
                },
                {
                  "type": "file",
                  "name": "img_59_start.jpg"
                },
                {
                  "type": "file",
                  "name": "img_5_end.jpg"
                },
                {
                  "type": "file",
                  "name": "img_5_start.jpg"
                },
                {
                  "type": "file",
                  "name": "img_60_end.jpg"
                },
                {
                  "type": "file",
                  "name": "img_60_start.jpg"
                },
                {
                  "type": "file",
                  "name": "img_61_end.jpg"
                },
                {
                  "type": "file",
                  "name": "img_61_start.jpg"
                },
                {
                  "type": "file",
                  "name": "img_62_end.jpg"
                },
                {
                  "type": "file",
                  "name": "img_62_start.jpg"
                },
                {
                  "type": "file",
                  "name": "img_63_end.jpg"
                },
                {
                  "type": "file",
                  "name": "img_63_start.jpg"
                },
                {
                  "type": "file",
                  "name": "img_64_end.jpg"
                },
                {
                  "type": "file",
                  "name": "img_64_start.jpg"
                },
                {
                  "type": "file",
                  "name": "img_65_end.jpg"
                },
                {
                  "type": "file",
                  "name": "img_65_start.jpg"
                },
                {
                  "type": "file",
                  "name": "img_66_end.jpg"
                },
                {
                  "type": "file",
                  "name": "img_66_start.jpg"
                },
                {
                  "type": "file",
                  "name": "img_67_end.jpg"
                },
                {
                  "type": "file",
                  "name": "img_67_start.jpg"
                },
                {
                  "type": "file",
                  "name": "img_68_end.jpg"
                },
                {
                  "type": "file",
                  "name": "img_68_start.jpg"
                },
                {
                  "type": "file",
                  "name": "img_69_end.jpg"
                },
                {
                  "type": "file",
                  "name": "img_69_start.jpg"
                },
                {
                  "type": "file",
                  "name": "img_6_end.jpg"
                },
                {
                  "type": "file",
                  "name": "img_6_start.jpg"
                },
                {
                  "type": "file",
                  "name": "img_70_end.jpg"
                },
                {
                  "type": "file",
                  "name": "img_70_start.jpg"
                },
                {
                  "type": "file",
                  "name": "img_71_end.jpg"
                },
                {
                  "type": "file",
                  "name": "img_71_start.jpg"
                },
                {
                  "type": "file",
                  "name": "img_72_end.jpg"
                },
                {
                  "type": "file",
                  "name": "img_72_start.jpg"
                },
                {
                  "type": "file",
                  "name": "img_73_end.jpg"
                },
                {
                  "type": "file",
                  "name": "img_73_start.jpg"
                },
                {
                  "type": "file",
                  "name": "img_74_end.jpg"
                },
                {
                  "type": "file",
                  "name": "img_74_start.jpg"
                },
                {
                  "type": "file",
                  "name": "img_75_end.jpg"
                },
                {
                  "type": "file",
                  "name": "img_75_start.jpg"
                },
                {
                  "type": "file",
                  "name": "img_76_end.jpg"
                },
                {
                  "type": "file",
                  "name": "img_76_start.jpg"
                },
                {
                  "type": "file",
                  "name": "img_77_end.jpg"
                },
                {
                  "type": "file",
                  "name": "img_77_start.jpg"
                },
                {
                  "type": "file",
                  "name": "img_78_end.jpg"
                },
                {
                  "type": "file",
                  "name": "img_78_start.jpg"
                },
                {
                  "type": "file",
                  "name": "img_79_end.jpg"
                },
                {
                  "type": "file",
                  "name": "img_79_start.jpg"
                },
                {
                  "type": "file",
                  "name": "img_7_end.jpg"
                },
                {
                  "type": "file",
                  "name": "img_7_start.jpg"
                },
                {
                  "type": "file",
                  "name": "img_80_end.jpg"
                },
                {
                  "type": "file",
                  "name": "img_80_start.jpg"
                },
                {
                  "type": "file",
                  "name": "img_81_end.jpg"
                },
                {
                  "type": "file",
                  "name": "img_81_start.jpg"
                },
                {
                  "type": "file",
                  "name": "img_82_end.jpg"
                },
                {
                  "type": "file",
                  "name": "img_82_start.jpg"
                },
                {
                  "type": "file",
                  "name": "img_83_end.jpg"
                },
                {
                  "type": "file",
                  "name": "img_83_start.jpg"
                },
                {
                  "type": "file",
                  "name": "img_84_end.jpg"
                },
                {
                  "type": "file",
                  "name": "img_84_start.jpg"
                },
                {
                  "type": "file",
                  "name": "img_85_end.jpg"
                },
                {
                  "type": "file",
                  "name": "img_85_start.jpg"
                },
                {
                  "type": "file",
                  "name": "img_86_end.jpg"
                },
                {
                  "type": "file",
                  "name": "img_86_start.jpg"
                },
                {
                  "type": "file",
                  "name": "img_87_end.jpg"
                },
                {
                  "type": "file",
                  "name": "img_87_start.jpg"
                },
                {
                  "type": "file",
                  "name": "img_88_end.jpg"
                },
                {
                  "type": "file",
                  "name": "img_88_start.jpg"
                },
                {
                  "type": "file",
                  "name": "img_89_end.jpg"
                },
                {
                  "type": "file",
                  "name": "img_89_start.jpg"
                },
                {
                  "type": "file",
                  "name": "img_8_end.jpg"
                },
                {
                  "type": "file",
                  "name": "img_8_start.jpg"
                },
                {
                  "type": "file",
                  "name": "img_90_end.jpg"
                },
                {
                  "type": "file",
                  "name": "img_90_start.jpg"
                },
                {
                  "type": "file",
                  "name": "img_91_end.jpg"
                },
                {
                  "type": "file",
                  "name": "img_91_start.jpg"
                },
                {
                  "type": "file",
                  "name": "img_92_end.jpg"
                },
                {
                  "type": "file",
                  "name": "img_92_start.jpg"
                },
                {
                  "type": "file",
                  "name": "img_93_end.jpg"
                },
                {
                  "type": "file",
                  "name": "img_93_start.jpg"
                },
                {
                  "type": "file",
                  "name": "img_94_end.jpg"
                },
                {
                  "type": "file",
                  "name": "img_94_start.jpg"
                },
                {
                  "type": "file",
                  "name": "img_95_end.jpg"
                },
                {
                  "type": "file",
                  "name": "img_95_start.jpg"
                },
                {
                  "type": "file",
                  "name": "img_96_end.jpg"
                },
                {
                  "type": "file",
                  "name": "img_96_start.jpg"
                },
                {
                  "type": "file",
                  "name": "img_97_end.jpg"
                },
                {
                  "type": "file",
                  "name": "img_97_start.jpg"
                },
                {
                  "type": "file",
                  "name": "img_98_end.jpg"
                },
                {
                  "type": "file",
                  "name": "img_98_start.jpg"
                },
                {
                  "type": "file",
                  "name": "img_99_end.jpg"
                },
                {
                  "type": "file",
                  "name": "img_99_start.jpg"
                },
                {
                  "type": "file",
                  "name": "img_9_end.jpg"
                },
                {
                  "type": "file",
                  "name": "img_9_start.jpg"
                }
              ]
            },
            {
              "type": "file",
              "name": "transcript.csv"
            }
          ]
        },
        {
          "type": "dir",
          "name": "static",
          "children": [
            {
              "type": "file",
              "name": "script.js"
            },
            {
              "type": "file",
              "name": "style.css"
            }
          ]
        },
        {
          "type": "dir",
          "name": "templates",
          "children": [
            {
              "type": "file",
              "name": "index.html"
            }
          ]
        },
        {
          "type": "file",
          "name": "image.index"
        },
        {
          "type": "file",
          "name": "rag_ingest.py"
        },
        {
          "type": "file",
          "name": "rag_mm.db"
        },
        {
          "type": "file",
          "name": "rag_query.py"
        },
        {
          "type": "file",
          "name": "requirements.txt"
        },
        {
          "type": "file",
          "name": "server.py"
        },
        {
          "type": "file",
          "name": "text.index"
        }
      ]
    },
    {
      "type": "file",
      "name": "README.md"
    }
  ]
}